histodata/__init__.py
histodata/dataset/__init__.py
histodata/dataset/dataset.py
histodata/helper/__init__.py
histodata/helper/collate_fn.py
histodata/sampler/__init__.py
histodata/sampler/sampler_balanced.py
histodata/sampler/sampler_simple.py
histodata-0.1.0.dist-info/LICENSE
histodata-0.1.0.dist-info/METADATA
histodata-0.1.0.dist-info/WHEEL
histodata-0.1.0.dist-info/top_level.txt
histodata-0.1.0.dist-info/RECORD
