Metadata-Version: 2.1
Name: histodata
Version: 0.1.0
Summary: A small example package
Home-page: https://git.tools.f4.htw-berlin.de/cbmi-charite/histodata
Author: Jonas Annuscheit
Author-email: Jonas.Annuscheit@htw-berlin.de
License: UNKNOWN
Platform: UNKNOWN
Classifier: Programming Language :: Python :: 3
Classifier: License :: OSI Approved :: MIT License
Classifier: Operating System :: OS Independent
Requires-Python: >=3.6
Requires-Dist: matplotlib
Requires-Dist: numpy
Requires-Dist: torch (>=1.5.1)
Requires-Dist: torchvision (>=0.6.1)
